ps3iso/__init__.py
ps3iso/__main__.py
ps3iso/game.py
ps3iso/sfo/__init__.py
ps3iso/sfo/_file.py
ps3iso/sfo/errors.py
ps3iso/sfo/file.py
ps3iso/sfo/parameters.py
ps3iso-0.4.1.dist-info/LICENSE
ps3iso-0.4.1.dist-info/METADATA
ps3iso-0.4.1.dist-info/WHEEL
ps3iso-0.4.1.dist-info/entry_points.txt
ps3iso-0.4.1.dist-info/top_level.txt
ps3iso-0.4.1.dist-info/RECORD
