Metadata-Version: 2.1
Name: ps3iso
Version: 0.4.1
Summary: CLI tool and Python library for managing Playstation 3 image files
Home-page: https://git.sr.ht/~jmstover/ps3iso
Author: Joshua Stover
Author-email: jmstover6@gmail.com
License: MIT
Project-URL: Documentation, https://ps3iso.readthedocs.io/en/stable
Project-URL: Source, https://git.sr.ht/~jmstover/ps3iso
Project-URL: Tracker, https://todo.sr.ht/~jmstover/ps3iso
Platform: UNKNOWN
Classifier: License :: OSI Approved :: MIT License
Classifier: Programming Language :: Python
Classifier: Programming Language :: Python :: 3
Classifier: Programming Language :: Python :: 3.6
Classifier: Programming Language :: Python :: 3.7
Requires-Python: >=3.6
